{"emmet.showSuggestionsAsSnippets": true,
 
  "emmet.includeLanguages": {
    "javascript": "javascriptreact", 
    "ejs": "html"
  },
 
  "emmet.triggerExpansionOnTab": true,
 
  "explorer.openEditors.visible": 0,

  "explorer.confirmDelete": false,

  "explorer.confirmDragAndDrop": false, 
  "diffEditor.ignoreTrimWhitespace": true,
 

  "editor.fontFamily": "'Fira Code', 'Cascadia Code', 'JetBrains Mono', Consolas, monospace",

    "editor.fontSize": 20,
  
  "editor.fontLigatures": true, 
  "editor.fontWeight": "300", 
  "editor.multiCursorModifier": "ctrlCmd", 

  "editor.minimap.enabled": false, 
  "editor.minimap.renderCharacters": false,

  "editor.wordWrap": "on", 
  "editor.lineHeight": 28,

  "editor.letterSpacing": 1,
 
  "editor.lineNumbers": "on", 
  "editor.cursorStyle": "block",
  "editor.formatOnPaste": true, 
  "editor.formatOnSave": false, 
  "editor.defaultFormatter": "esbenp.prettier-vscode", 
  
  "editor.matchBrackets": "never",
  
  "editor.detectIndentation": false,
  
  "editor.tabSize": 2,
  
  "editor.cursorWidth": 2,
  
  "editor.snippetSuggestions": "top",
  
  "editor.renderControlCharacters": true,

  "editor.wordWrapColumn": 100,
  "editor.selectionHighlight": true, 
  "editor.quickSuggestions": { 
    "other": true,
    "comments": false,
    "strings": false
  },
  "editor.mouseWheelZoom": true, 
  "editor.rulers": [
    120
  ],
  "editor.renderLineHighlight": "line", 
  
  "editor.codeActionsOnSave": {
  },
  "editor.tabCompletion":"on"
  }
